balkanid/__init__.py
balkanid/client.py
balkanid/core/__init__.py
balkanid/core/api_error.py
balkanid/core/client_wrapper.py
balkanid/core/datetime_utils.py
balkanid/core/jsonable_encoder.py
balkanid/core/remove_none_from_dict.py
balkanid/environment.py
balkanid/helpers.py
balkanid/py.typed
balkanid/resources/__init__.py
balkanid/resources/campaigns/__init__.py
balkanid/resources/campaigns/client.py
balkanid/resources/employees/__init__.py
balkanid/resources/employees/client.py
balkanid/resources/integrations/__init__.py
balkanid/resources/integrations/client.py
balkanid/resources/relations/__init__.py
balkanid/resources/relations/client.py
balkanid/resources/requests/__init__.py
balkanid/resources/requests/client.py
balkanid/resources/reviews/__init__.py
balkanid/resources/reviews/client.py
balkanid/types/__init__.py
balkanid/types/download_url_response.py
balkanid/types/error.py
balkanid/types/review_download_url_request_filter.py
balkanid/types/review_download_url_request_filter_campaign.py
balkanid/types/review_download_url_request_filter_request.py
balkanid/types/review_upload_url_request.py
balkanid/types/upload_url_response.py
fern_balkan_id-0.0.11.dist-info/METADATA
fern_balkan_id-0.0.11.dist-info/WHEEL
fern_balkan_id-0.0.11.dist-info/RECORD
